[
  {
    "author": "Ömer Y.",
    "date" : "3 hafta önce",
    "author_first_letter" : "OY",
    "comment": "Her seviye için uygun, hocamız her şeyi açıklamış. Bana çok faydası oldu kesinlikle tavsiye ederim.\n"
  },
  {
    "author": "Cevher Hakan K.",
    "date" : "1 ay önce",
    "author_first_letter" : "CK",
    "comment": "Kursu yaklaşık 2 yıllık bir sürede sindire sindire bitirdim. Sadece son sertifika sınavım kaldı. Hiç bilmeyenler belki bir tık zorlanabilir ama vazgeçmezseniz büyük kazanım sağlarsınız."
  },
  {
    "author": "Yakup K.",
    "date" : "2 ay önce",
    "author_first_letter" : "YK",
    "comment": "Emeğiniz için teşekkür ederim.\n"
  },
  {
    "author": "Ibrahim Z.",
    "date" : "3 gün önce",
    "author_first_letter" : "IZ",
    "comment": "Şuanlık güzel gidiyor, kursun daha başında sayılırım umarım kursu bitirdikten sonra istediğim seviyeye ulaşırım."
  }



]